backtrader/__init__.py
backtrader/analyzer.py
backtrader/broker.py
backtrader/cerebro.py
backtrader/comminfo.py
backtrader/dataseries.py
backtrader/errors.py
backtrader/feed.py
backtrader/fillers.py
backtrader/flt.py
backtrader/functions.py
backtrader/indicator.py
backtrader/linebuffer.py
backtrader/lineiterator.py
backtrader/lineroot.py
backtrader/lineseries.py
backtrader/mathsupport.py
backtrader/metabase.py
backtrader/observer.py
backtrader/order.py
backtrader/position.py
backtrader/resamplerfilter.py
backtrader/signal.py
backtrader/sizer.py
backtrader/store.py
backtrader/strategy.py
backtrader/talib.py
backtrader/timer.py
backtrader/trade.py
backtrader/tradingcal.py
backtrader/version.py
backtrader/writer.py
highcharts/__init__.py
highcharts/ipynb.py
highcharts/plotHelpbylw.py
highcharts/version.py
highcharts/__pycache__/__init__.cpython-36.pyc
highcharts/__pycache__/__init__.cpython-37.pyc
highcharts/__pycache__/ipynb.cpython-36.pyc
highcharts/__pycache__/ipynb.cpython-37.pyc
highcharts/__pycache__/plotHelpbylw.cpython-36.pyc
highcharts/__pycache__/plotHelpbylw.cpython-37.pyc
highcharts/__pycache__/version.cpython-36.pyc
highcharts/__pycache__/version.cpython-37.pyc
highcharts/highcharts/__init__.py
highcharts/highcharts/common.py
highcharts/highcharts/highchart_types.py
highcharts/highcharts/highcharts.py
highcharts/highcharts/options.py
highcharts/highcharts/__pycache__/__init__.cpython-36.pyc
highcharts/highcharts/__pycache__/__init__.cpython-37.pyc
highcharts/highcharts/__pycache__/common.cpython-36.pyc
highcharts/highcharts/__pycache__/common.cpython-37.pyc
highcharts/highcharts/__pycache__/highchart_types.cpython-36.pyc
highcharts/highcharts/__pycache__/highchart_types.cpython-37.pyc
highcharts/highcharts/__pycache__/highcharts.cpython-36.pyc
highcharts/highcharts/__pycache__/highcharts.cpython-37.pyc
highcharts/highcharts/__pycache__/options.cpython-36.pyc
highcharts/highcharts/__pycache__/options.cpython-37.pyc
highcharts/highcharts/templates/base.html
highcharts/quantlwsdk.egg-info/PKG-INFO
highcharts/quantlwsdk.egg-info/SOURCES.txt
highcharts/quantlwsdk.egg-info/dependency_links.txt
highcharts/quantlwsdk.egg-info/top_level.txt
quantlwsdk-0.0.18.dist-info/METADATA
quantlwsdk-0.0.18.dist-info/WHEEL
quantlwsdk-0.0.18.dist-info/top_level.txt
quantlwsdk-0.0.18.dist-info/RECORD
