Metadata-Version: 2.1
Name: quantlwsdk
Version: 0.0.18
Summary: 量化辅助sdk
Home-page: https://github.com
Author: lw
Author-email: 100000@qq.com
License: UNKNOWN
Platform: UNKNOWN
